generichelpers/__init__.py
generichelpers/app.py
generichelpers/appst.py
generichelpers/.streamlit/com.ratnadip.streamlitapp.plist
generichelpers/.streamlit/config.toml
generichelpers/.streamlit/emojis.json
generichelpers/.streamlit/pages.toml
generichelpers/.streamlit/run_streamlit.sh
generichelpers/.streamlit/secrets.toml
generichelpers/apiroutes/__init__.py
generichelpers/apiroutes/calctimeapis.py
generichelpers/apiroutes/moviemanageapis.py
generichelpers/configs/__init__.py
generichelpers/configs/config.yaml
generichelpers/data/__init__.py
generichelpers/data/english_words.p
generichelpers/devs/__init__.py
generichelpers/devs/moviemanager.py
generichelpers/devs/payslipparser.py
generichelpers/pages/__init__.py
generichelpers/pages/calctime.py
generichelpers/pages/filesmanager.py
generichelpers/pages/home.py
generichelpers/pages/initilizer.py
generichelpers/pages/moviefetcher.py
generichelpers/pages/moviegenretagger.py
generichelpers/pages/moviesorter.py
generichelpers/pages/moviessummarizer.py
generichelpers/pages/parsepayslip.py
generichelpers/utils/__init__.py
generichelpers/utils/dsmiscutils.py
generichelpers/utils/dtypesutils.py
generichelpers/utils/fileopsutils.py
generichelpers/utils/genericutils.py
generichelpers/utils/logger.py
generichelpers/utils/textclean.py
generichelpers/utils/timeutils.py
generichelpers-1.5.dist-info/METADATA
generichelpers-1.5.dist-info/WHEEL
generichelpers-1.5.dist-info/top_level.txt
generichelpers-1.5.dist-info/RECORD
