Metadata-Version: 2.4
Name: generichelpers
Version: 1.5
Summary: Generic Helper Modules
Home-page: https://gitlab.com/adhikari.ratan/generic-helpers.git
Download-URL: https://gitlab.com/adhikari.ratan/generic-helpers
Author: Ratnadip Adhikari
Author-email: ratnadip.adhikari@gmail.com
Keywords: utilities,python,helper modules
Platform: any
Classifier: Development Status :: 4 - Beta
Classifier: Intended Audience :: Developers
Classifier: Operating System :: OS Independent
Classifier: Programming Language :: Python :: 3
Classifier: Topic :: Utilities
Dynamic: author
Dynamic: author-email
Dynamic: classifier
Dynamic: description
Dynamic: download-url
Dynamic: home-page
Dynamic: keywords
Dynamic: platform
Dynamic: summary
